unicef_realm/__init__.py
unicef_realm/admin.py
unicef_realm/apps.py
unicef_realm/config.py
unicef_realm/graph.py
unicef_realm/models.py
unicef_realm/sync.py
unicef_realm/tasks.py
unicef_realm/migrations/0001_initial.py
unicef_realm/migrations/__init__.py
unicef_realm/templates/admin/unicef_realm/add_grants.html
unicef_realm-0.1.dist-info/LICENSE
unicef_realm-0.1.dist-info/METADATA
unicef_realm-0.1.dist-info/WHEEL
unicef_realm-0.1.dist-info/top_level.txt
unicef_realm-0.1.dist-info/RECORD
