Metadata-Version: 2.1
Name: unicef-realm
Version: 0.1
Summary: Provides Business Area and User Role permission management
Home-page: https://github.com/unicef/unicef-business-areas
Author: UNICEF
Author-email: rapidpro@unicef.org
License: Apache 2 License
Platform: any
Classifier: Environment :: Web Environment
Classifier: Programming Language :: Python :: 3.9
Classifier: Framework :: Django
Classifier: Framework :: Django :: 3.2
Classifier: Framework :: Django :: 4.0
Classifier: Intended Audience :: Developers
License-File: LICENSE
Requires-Dist: celery
Requires-Dist: cryptography
Requires-Dist: django
Requires-Dist: django-admin-extra-buttons
Requires-Dist: django-constance
Requires-Dist: django-countries
Requires-Dist: django-picklefield
Requires-Dist: requests
Provides-Extra: test
Requires-Dist: django-webtest ; extra == 'test'
Requires-Dist: factory-boy ; extra == 'test'
Requires-Dist: flake8 ; extra == 'test'
Requires-Dist: httpretty ; extra == 'test'
Requires-Dist: isort ; extra == 'test'
Requires-Dist: mock ; extra == 'test'
Requires-Dist: pytest ; extra == 'test'
Requires-Dist: pytest-cov ; extra == 'test'
Requires-Dist: pytest-django ; extra == 'test'
Requires-Dist: pytest-echo ; extra == 'test'
Requires-Dist: pytest-redis ; extra == 'test'
Requires-Dist: requests-mock ; extra == 'test'
Requires-Dist: unittest2 ; extra == 'test'
Requires-Dist: vcrpy ; extra == 'test'
